LICENSE
README.md
pyproject.toml
setup.cfg
setup.py
audups/__init__.py
audups/__main__.py
audups/common.py
audups/compare.py
audups/correlate.c
audups/fingerprint.py
audups/pool_lazy_map.py
audups.egg-info/PKG-INFO
audups.egg-info/SOURCES.txt
audups.egg-info/dependency_links.txt
audups.egg-info/entry_points.txt
audups.egg-info/requires.txt
audups.egg-info/top_level.txt